lomatching/__init__.py
lomatching/decoder.py
lomatching/util.py
lomatching-0.2.2.dist-info/licenses/LICENSE
lomatching-0.2.2.dist-info/METADATA
lomatching-0.2.2.dist-info/WHEEL
lomatching-0.2.2.dist-info/top_level.txt
lomatching-0.2.2.dist-info/RECORD
