Metadata-Version: 2.4
Name: lomatching
Version: 0.2.2
Summary: Logical observable decoder for transversal logical gates in surface codes based on pymatching.
Author-email: Marc Serra Peralta <marcserraperalta@gmail.com>
Maintainer-email: Marc Serra Peralta <marcserraperalta@gmail.com>
License: MIT License
Keywords: MWPM,QEC,quantum error correction,logical-gates,decoder
Requires-Python: >=3.10
License-File: LICENSE
Requires-Dist: numpy
Requires-Dist: stim
Requires-Dist: pymatching
Requires-Dist: matplotlib
Requires-Dist: galois
Requires-Dist: ldpc
Requires-Dist: numba
Provides-Extra: dev
Requires-Dist: pip-tools; extra == "dev"
Requires-Dist: pytest; extra == "dev"
Requires-Dist: black; extra == "dev"
Requires-Dist: pytest-black; extra == "dev"
Requires-Dist: flake8; extra == "dev"
Requires-Dist: flake8-print; extra == "dev"
Requires-Dist: pytest-flake8; extra == "dev"
Requires-Dist: surface-sim>=0.10.0; extra == "dev"
Requires-Dist: gprof2dot; extra == "dev"
Dynamic: license-file
